{
  "pageId": "app.menu",
  "surface": "app",
  "route": "/{companyId}/{locale}/menu",
  "version": 1,
  "sourceHash": "sha256:9c41074394ed74e34faca64407864a68acf98a8b2e7061fff2711321c07403bc",
  "keys": {
    "checkIn": "Check-in",
    "leaves": "Leaves",
    "expenses": "Expenses",
    "payroll": "Payroll",
    "checklist": "Checklist",
    "myAi": "AI Agent",
    "billing": "Billing",
    "notices": "Notices",
    "noticeTooltip": "Notice",
    "dashboard": "Dashboard",
    "invoices": "Invoices",
    "customers": "Customer",
    "crm": "CRM",
    "accounting": "Accounting",
    "payment": "Payment",
    "financialReports": "Financial Reports",
    "reservation": "Reservation",
    "calendar": "Calendar",
    "mailing": "Mailing"
  },
  "meta": {
    "productRepo": "core-platform",
    "sourcePath": "apps/employee-web/dictionaries/en.json#menu",
    "githubPath": "app/menu.page.json"
  }
}
